idem_random/conf.py
idem_random/scripts.py
idem_random/version.py
idem_random/exec/init.py
idem_random/exec/random/password.py
idem_random/idem_random/init.py
idem_random/states/init.py
idem_random/states/random/id.py
idem_random/states/random/integer.py
idem_random/states/random/password.py
idem_random/tool/init.py
idem_random/tool/random/id.py
idem_random-2.0.0.dist-info/LICENSE
idem_random-2.0.0.dist-info/METADATA
idem_random-2.0.0.dist-info/WHEEL
idem_random-2.0.0.dist-info/entry_points.txt
idem_random-2.0.0.dist-info/top_level.txt
idem_random-2.0.0.dist-info/RECORD
